SubjData/__init__.py
SubjData/download.py
SubjData/main.py
SubjData/process.py
SubjData/update.py
SubjData/resources/__init__.py
SubjData/resources/download_dict.json
SubjData/resources/instruction_dict.json
SubjData/resources/mapping_original.json
SubjData/resources/overview_dict_original.json
SubjData/resources/process_dict.json
SubjData/resources/taxonomoy_original.json
SubjData/resources/utils.py
SubjData-0.1.13.dist-info/METADATA
SubjData-0.1.13.dist-info/WHEEL
SubjData-0.1.13.dist-info/top_level.txt
SubjData-0.1.13.dist-info/RECORD
