Metadata-Version: 2.1
Name: SubjData
Version: 0.1.13
Summary: A library for automatically creating targeted hate speech datasets.
Author: Leon Fröhling
Author-email: leon.froehling@gesis.org
Classifier: Programming Language :: Python :: 3
Classifier: License :: OSI Approved :: MIT License
Classifier: Operating System :: OS Independent
Requires-Python: >=3.10
Requires-Dist: pandas
Requires-Dist: numpy
Requires-Dist: huggingface-hub
Requires-Dist: pyarrow
Requires-Dist: fastparquet
